facture_electronique/__init__.py
facture_electronique/constructeur.py
facture_electronique/exceptions.py
facture_electronique/models.py
facture_electronique/afnor_client/__init__.py
facture_electronique/afnor_client/client.py
facture_electronique/afnor_client/monitoring.py
facture_electronique/afnor_client/serveur_mock.py
facture_electronique/afnor_client/swagger/ANNEXE A - PR XP Z12-013 - AFNOR-Directory_Service-1.0.0-swagger.json
facture_electronique/afnor_client/swagger/ANNEXE B - PR XP Z12-013 - AFNOR-Flow_Service-1.0.2-swagger.json
facture_electronique/afnor_client/test/conftest.py
facture_electronique/afnor_client/test/test_api_client.py
facture_electronique/afnor_client/test/test_integration.py
facture_electronique/afnor_client/test/test_monitoring.py
facture_electronique/afnor_client/test/test_serveur_mock.py
facture_electronique/api/__init__.py
facture_electronique/api/chorus_pro.py
facture_electronique/api/pannylane.py
facture_electronique/api/sage.py
facture_electronique/api/swagger/Factures.json
facture_electronique/api/swagger/Structures.json
facture_electronique/api/test/test_chorus_pro_api.py
facture_electronique/exemples/__init__.py
facture_electronique/exemples/dummy.pdf
facture_electronique/exemples/exemple.py
facture_electronique/exemples/exemple_decoupe.py
facture_electronique/generated/__init__.py
facture_electronique/generated/factur_x_1_07_02/__init__.py
facture_electronique/generated/factur_x_1_07_02/factur_x_basic/__init__.py
facture_electronique/generated/factur_x_1_07_02/factur_x_basic/factur_x_1_07_2_basic.py
facture_electronique/generated/factur_x_1_07_02/factur_x_basic/factur_x_1_07_2_basic_urn_un_unece_uncefact_data_standard_qualified_data_type_100.py
facture_electronique/generated/factur_x_1_07_02/factur_x_basic/factur_x_1_07_2_basic_urn_un_unece_uncefact_data_standard_reusable_aggregate_business_information_entity_100.py
facture_electronique-0.8.4.dist-info/licenses/LICENSE
facture_electronique-0.8.4.dist-info/METADATA
facture_electronique-0.8.4.dist-info/WHEEL
facture_electronique-0.8.4.dist-info/entry_points.txt
facture_electronique-0.8.4.dist-info/top_level.txt
facture_electronique-0.8.4.dist-info/RECORD
