Metadata-Version: 2.4
Name: facture_electronique
Version: 0.8.4
Summary: Facturation Electronique SDK est une bibliothèque Python qui simplifie l'interaction avec les principales API de facturation électronique en France, notamment **Chorus Pro**, et d'autres partenaires privés. Elle supporte également le format Factur-X pour la création et l'envoi de factures électroniques.
Author-email: Thierry Martin <thierry.martin.2008@gadz.org>
License: MIT
Project-URL: Homepage, https://github.com/thierryjmartin/facturation_electronique
Project-URL: Source Code, https://github.com/thierryjmartin/facturation_electronique
Project-URL: Documentation, https://thierryjmartin.github.io/facturation_electronique/
Keywords: chorus pro,choruspro,facturx,factur-x,facture électronique,EN16931,invoice
Classifier: Development Status :: 3 - Alpha
Classifier: Programming Language :: Python :: 3
Classifier: Intended Audience :: Developers
Classifier: Operating System :: OS Independent
Classifier: Topic :: Office/Business :: Financial :: Accounting
Classifier: License :: OSI Approved :: MIT License
Requires-Python: >=3.10
License-File: LICENSE
Requires-Dist: requests>=2.32.3
Requires-Dist: python-dateutil>=2.8.2
Requires-Dist: pydantic>=2.9.2
Requires-Dist: factur-x>=3.4
Requires-Dist: ghostscript>=0.7
Requires-Dist: xsdata>=24.9
Requires-Dist: saxonche>=12.5.0
Requires-Dist: pyHanko[image-support,opentype,pkcs11]>=0.25.3
Provides-Extra: test
Requires-Dist: pytest; extra == "test"
Requires-Dist: pytest-cov; extra == "test"
Requires-Dist: pytest-markdown-docs; extra == "test"
Provides-Extra: dev
Requires-Dist: ruff; extra == "dev"
Requires-Dist: pre-commit; extra == "dev"
Requires-Dist: pip-tools; extra == "dev"
Requires-Dist: facture-electronique[test]; extra == "dev"
Dynamic: license-file
